logstamp/__init__.py
logstamp-0.1.0.dist-info/WHEEL
logstamp-0.1.0.dist-info/METADATA
logstamp-0.1.0.dist-info/RECORD
