Metadata-Version: 2.1
Name: logstamp
Version: 0.1.0
Summary: Logstamp console and file log.
Author: Andrew MAtte
Author-email: andrew.matte@gmail.com
Requires-Python: >=3.6
Classifier: Programming Language :: Python :: 3
Classifier: Programming Language :: Python :: 3.10
Classifier: Programming Language :: Python :: 3.6
Classifier: Programming Language :: Python :: 3.7
Classifier: Programming Language :: Python :: 3.8
Classifier: Programming Language :: Python :: 3.9
